Workbook

Sheet Measured run and cost inputs
A1: Measured run and cost inputs
A2: ReachPilot unit economics · Main Scenario
A4: Variable / dimension | B4: Value
A5: Run credits spent | B5: =53.06 -> 53.06
A6: Run qualified leads | B6: =10 -> 10
A7: Credits per qualified lead | B7: ='Measured run and cost inputs'!B5/'Measured run and cost inputs'!B6 -> 5.306
A8: v0 credits per qualified lead | B8: =14.6 -> 14.6
A9: Credit reduction | B9: ='Measured run and cost inputs'!B8-'Measured run and cost inputs'!B7 -> 9.294
A10: Credit reduction percent | B10: ='Measured run and cost inputs'!B9/'Measured run and cost inputs'!B8 -> 0.63657534
A11: Run cache hit rate | B11: =0.246 -> 0.246
A12: Low credit price | B12: =0.05 -> 0.05
A13: High credit price | B13: =0.06 -> 0.06
A14: Data cost per lead low | B14: ='Measured run and cost inputs'!B7*'Measured run and cost inputs'!B12 -> 0.2653
A15: Data cost per lead high | B15: ='Measured run and cost inputs'!B7*'Measured run and cost inputs'!B13 -> 0.31836
A16: Hosting monthly | B16: =20 -> 20
A17: Email monthly | B17: =20 -> 20
A18: LLM cost per lead | B18: ='Campaign LLM measurement'!B5/'Measured run and cost inputs'!B6 -> 0.0102092
A19: Fixed monthly overhead | B19: ='Measured run and cost inputs'!B16+'Measured run and cost inputs'!B17 -> 40

Sheet Monthly operating case
A1: Monthly operating case
A2: ReachPilot unit economics · Main Scenario
A4: Variable / dimension | B4: Value
A5: Active customers | B5: =40 -> 40
A6: Leads per customer | B6: =100 -> 100
A7: Monthly customer churn | B7: =0.05 -> 0.05
A8: Qualified leads monthly | B8: ='Monthly operating case'!B5*'Monthly operating case'!B6 -> 4000
A9: Credits required monthly | B9: ='Monthly operating case'!B8*'Measured run and cost inputs'!B7 -> 21224
A10: Replacement customers monthly | B10: ='Monthly operating case'!B5*'Monthly operating case'!B7 -> 2
A11: Cost floor per lead low | B11: ='Measured run and cost inputs'!B14+'Measured run and cost inputs'!B19/'Monthly operating case'!B8 -> 0.2753
A12: Cost floor per lead high | B12: ='Measured run and cost inputs'!B15+'Measured run and cost inputs'!B19/'Monthly operating case'!B8 -> 0.32836
A13: Blended cost per lead low | B13: =IF('Measured run and cost inputs'!B18="","",'Monthly operating case'!B11+'Measured run and cost inputs'!B18) -> 0.2855092
A14: Blended cost per lead high | B14: =IF('Measured run and cost inputs'!B18="","",'Monthly operating case'!B12+'Measured run and cost inputs'!B18) -> 0.3385692
A15: Bedrock monthly inference | B15: =IF('Measured run and cost inputs'!B18="","",'Monthly operating case'!B8*'Measured run and cost inputs'!B18) -> 40.8368

Sheet Pricing comparison
A1: Pricing comparison
A2: ReachPilot unit economics · Main Scenario
A4: Variable / dimension | B4: Subscription fee | C4: Price per delivered lead | D4: Revenue per customer | E4: Revenue per qualified lead | F4: Monthly plan revenue | G4: Surplus before LLM low | H4: Surplus before LLM high | I4: Break-even customer floor low | J4: Break-even customer floor high | K4: Full break-even customers high | L4: LLM allowance per lead before loss
A5: $0.80 per lead | B5: =0 -> 0 | C5: =0.8 -> 0.8 | D5: ='Pricing comparison'!B5+'Pricing comparison'!C5*'Monthly operating case'!B6 -> 80 | E5: ='Pricing comparison'!D5/'Monthly operating case'!B6 -> 0.8 | F5: ='Pricing comparison'!D5*'Monthly operating case'!B5 -> 3200 | G5: ='Pricing comparison'!F5-'Monthly operating case'!B8*'Measured run and cost inputs'!B14-'Measured run and cost inputs'!B19 -> 2098.8 | H5: ='Pricing comparison'!F5-'Monthly operating case'!B8*'Measured run and cost inputs'!B15-'Measured run and cost inputs'!B19 -> 1886.56 | I5: =IF(IF(IF(ISERROR('Pricing comparison'!D5>'Monthly operating case'!B6*'Measured run and cost inputs'!B14),'Pricing comparison'!D5>'Monthly operating case'!B6*'Measured run and cost inputs'!B14,IF('Pricing comparison'!D5="","",'Pricing comparison'!D5>'Monthly operating case'!B6*'Measured run and cost inputs'!B14))="",FALSE,IF(ISERROR('Pricing comparison'!D5>'Monthly operating case'!B6*'Measured run and cost inputs'!B14),'Pricing comparison'!D5>'Monthly operating case'!B6*'Measured run and cost inputs'!B14,IF('Pricing comparison'!D5="","",'Pricing comparison'!D5>'Monthly operating case'!B6*'Measured run and cost inputs'!B14))),CEILING('Measured run and cost inputs'!B19/('Pricing comparison'!D5-'Monthly operating case'!B6*'Measured run and cost inputs'!B14),1),"") -> 1 | J5: =IF(IF(IF(ISERROR('Pricing comparison'!D5>'Monthly operating case'!B6*'Measured run and cost inputs'!B15),'Pricing comparison'!D5>'Monthly operating case'!B6*'Measured run and cost inputs'!B15,IF('Pricing comparison'!D5="","",'Pricing comparison'!D5>'Monthly operating case'!B6*'Measured run and cost inputs'!B15))="",FALSE,IF(ISERROR('Pricing comparison'!D5>'Monthly operating case'!B6*'Measured run and cost inputs'!B15),'Pricing comparison'!D5>'Monthly operating case'!B6*'Measured run and cost inputs'!B15,IF('Pricing comparison'!D5="","",'Pricing comparison'!D5>'Monthly operating case'!B6*'Measured run and cost inputs'!B15))),CEILING('Measured run and cost inputs'!B19/('Pricing comparison'!D5-'Monthly operating case'!B6*'Measured run and cost inputs'!B15),1),"") -> 1 | K5: =IF('Measured run and cost inputs'!B18="","",IF(IF(IF(ISERROR('Pricing comparison'!D5>'Monthly operating case'!B6*('Measured run and cost inputs'!B15+'Measured run and cost inputs'!B18)),'Pricing comparison'!D5>'Monthly operating case'!B6*('Measured run and cost inputs'!B15+'Measured run and cost inputs'!B18),IF('Pricing comparison'!D5="","",'Pricing comparison'!D5>'Monthly operating case'!B6*('Measured run and cost inputs'!B15+'Measured run and cost inputs'!B18)))="",FALSE,IF(ISERROR('Pricing comparison'!D5>'Monthly operating case'!B6*('Measured run and cost inputs'!B15+'Measured run and cost inputs'!B18)),'Pricing comparison'!D5>'Monthly operating case'!B6*('Measured run and cost inputs'!B15+'Measured run and cost inputs'!B18),IF('Pricing comparison'!D5="","",'Pricing comparison'!D5>'Monthly operating case'!B6*('Measured run and cost inputs'!B15+'Measured run and cost inputs'!B18)))),CEILING('Measured run and cost inputs'!B19/('Pricing comparison'!D5-'Monthly operating case'!B6*('Measured run and cost inputs'!B15+'Measured run and cost inputs'!B18)),1),"")) -> 1 | L5: ='Pricing comparison'!E5-'Monthly operating case'!B12 -> 0.47164
A6: $49 subscription | B6: =49 -> 49 | C6: =0 -> 0 | D6: ='Pricing comparison'!B6+'Pricing comparison'!C6*'Monthly operating case'!B6 -> 49 | E6: ='Pricing comparison'!D6/'Monthly operating case'!B6 -> 0.49 | F6: ='Pricing comparison'!D6*'Monthly operating case'!B5 -> 1960 | G6: ='Pricing comparison'!F6-'Monthly operating case'!B8*'Measured run and cost inputs'!B14-'Measured run and cost inputs'!B19 -> 858.8 | H6: ='Pricing comparison'!F6-'Monthly operating case'!B8*'Measured run and cost inputs'!B15-'Measured run and cost inputs'!B19 -> 646.56 | I6: =IF(IF(IF(ISERROR('Pricing comparison'!D6>'Monthly operating case'!B6*'Measured run and cost inputs'!B14),'Pricing comparison'!D6>'Monthly operating case'!B6*'Measured run and cost inputs'!B14,IF('Pricing comparison'!D6="","",'Pricing comparison'!D6>'Monthly operating case'!B6*'Measured run and cost inputs'!B14))="",FALSE,IF(ISERROR('Pricing comparison'!D6>'Monthly operating case'!B6*'Measured run and cost inputs'!B14),'Pricing comparison'!D6>'Monthly operating case'!B6*'Measured run and cost inputs'!B14,IF('Pricing comparison'!D6="","",'Pricing comparison'!D6>'Monthly operating case'!B6*'Measured run and cost inputs'!B14))),CEILING('Measured run and cost inputs'!B19/('Pricing comparison'!D6-'Monthly operating case'!B6*'Measured run and cost inputs'!B14),1),"") -> 2 | J6: =IF(IF(IF(ISERROR('Pricing comparison'!D6>'Monthly operating case'!B6*'Measured run and cost inputs'!B15),'Pricing comparison'!D6>'Monthly operating case'!B6*'Measured run and cost inputs'!B15,IF('Pricing comparison'!D6="","",'Pricing comparison'!D6>'Monthly operating case'!B6*'Measured run and cost inputs'!B15))="",FALSE,IF(ISERROR('Pricing comparison'!D6>'Monthly operating case'!B6*'Measured run and cost inputs'!B15),'Pricing comparison'!D6>'Monthly operating case'!B6*'Measured run and cost inputs'!B15,IF('Pricing comparison'!D6="","",'Pricing comparison'!D6>'Monthly operating case'!B6*'Measured run and cost inputs'!B15))),CEILING('Measured run and cost inputs'!B19/('Pricing comparison'!D6-'Monthly operating case'!B6*'Measured run and cost inputs'!B15),1),"") -> 3 | K6: =IF('Measured run and cost inputs'!B18="","",IF(IF(IF(ISERROR('Pricing comparison'!D6>'Monthly operating case'!B6*('Measured run and cost inputs'!B15+'Measured run and cost inputs'!B18)),'Pricing comparison'!D6>'Monthly operating case'!B6*('Measured run and cost inputs'!B15+'Measured run and cost inputs'!B18),IF('Pricing comparison'!D6="","",'Pricing comparison'!D6>'Monthly operating case'!B6*('Measured run and cost inputs'!B15+'Measured run and cost inputs'!B18)))="",FALSE,IF(ISERROR('Pricing comparison'!D6>'Monthly operating case'!B6*('Measured run and cost inputs'!B15+'Measured run and cost inputs'!B18)),'Pricing comparison'!D6>'Monthly operating case'!B6*('Measured run and cost inputs'!B15+'Measured run and cost inputs'!B18),IF('Pricing comparison'!D6="","",'Pricing comparison'!D6>'Monthly operating case'!B6*('Measured run and cost inputs'!B15+'Measured run and cost inputs'!B18)))),CEILING('Measured run and cost inputs'!B19/('Pricing comparison'!D6-'Monthly operating case'!B6*('Measured run and cost inputs'!B15+'Measured run and cost inputs'!B18)),1),"")) -> 3 | L6: ='Pricing comparison'!E6-'Monthly operating case'!B12 -> 0.16164
A7: $99 subscription | B7: =99 -> 99 | C7: =0 -> 0 | D7: ='Pricing comparison'!B7+'Pricing comparison'!C7*'Monthly operating case'!B6 -> 99 | E7: ='Pricing comparison'!D7/'Monthly operating case'!B6 -> 0.99 | F7: ='Pricing comparison'!D7*'Monthly operating case'!B5 -> 3960 | G7: ='Pricing comparison'!F7-'Monthly operating case'!B8*'Measured run and cost inputs'!B14-'Measured run and cost inputs'!B19 -> 2858.8 | H7: ='Pricing comparison'!F7-'Monthly operating case'!B8*'Measured run and cost inputs'!B15-'Measured run and cost inputs'!B19 -> 2646.56 | I7: =IF(IF(IF(ISERROR('Pricing comparison'!D7>'Monthly operating case'!B6*'Measured run and cost inputs'!B14),'Pricing comparison'!D7>'Monthly operating case'!B6*'Measured run and cost inputs'!B14,IF('Pricing comparison'!D7="","",'Pricing comparison'!D7>'Monthly operating case'!B6*'Measured run and cost inputs'!B14))="",FALSE,IF(ISERROR('Pricing comparison'!D7>'Monthly operating case'!B6*'Measured run and cost inputs'!B14),'Pricing comparison'!D7>'Monthly operating case'!B6*'Measured run and cost inputs'!B14,IF('Pricing comparison'!D7="","",'Pricing comparison'!D7>'Monthly operating case'!B6*'Measured run and cost inputs'!B14))),CEILING('Measured run and cost inputs'!B19/('Pricing comparison'!D7-'Monthly operating case'!B6*'Measured run and cost inputs'!B14),1),"") -> 1 | J7: =IF(IF(IF(ISERROR('Pricing comparison'!D7>'Monthly operating case'!B6*'Measured run and cost inputs'!B15),'Pricing comparison'!D7>'Monthly operating case'!B6*'Measured run and cost inputs'!B15,IF('Pricing comparison'!D7="","",'Pricing comparison'!D7>'Monthly operating case'!B6*'Measured run and cost inputs'!B15))="",FALSE,IF(ISERROR('Pricing comparison'!D7>'Monthly operating case'!B6*'Measured run and cost inputs'!B15),'Pricing comparison'!D7>'Monthly operating case'!B6*'Measured run and cost inputs'!B15,IF('Pricing comparison'!D7="","",'Pricing comparison'!D7>'Monthly operating case'!B6*'Measured run and cost inputs'!B15))),CEILING('Measured run and cost inputs'!B19/('Pricing comparison'!D7-'Monthly operating case'!B6*'Measured run and cost inputs'!B15),1),"") -> 1 | K7: =IF('Measured run and cost inputs'!B18="","",IF(IF(IF(ISERROR('Pricing comparison'!D7>'Monthly operating case'!B6*('Measured run and cost inputs'!B15+'Measured run and cost inputs'!B18)),'Pricing comparison'!D7>'Monthly operating case'!B6*('Measured run and cost inputs'!B15+'Measured run and cost inputs'!B18),IF('Pricing comparison'!D7="","",'Pricing comparison'!D7>'Monthly operating case'!B6*('Measured run and cost inputs'!B15+'Measured run and cost inputs'!B18)))="",FALSE,IF(ISERROR('Pricing comparison'!D7>'Monthly operating case'!B6*('Measured run and cost inputs'!B15+'Measured run and cost inputs'!B18)),'Pricing comparison'!D7>'Monthly operating case'!B6*('Measured run and cost inputs'!B15+'Measured run and cost inputs'!B18),IF('Pricing comparison'!D7="","",'Pricing comparison'!D7>'Monthly operating case'!B6*('Measured run and cost inputs'!B15+'Measured run and cost inputs'!B18)))),CEILING('Measured run and cost inputs'!B19/('Pricing comparison'!D7-'Monthly operating case'!B6*('Measured run and cost inputs'!B15+'Measured run and cost inputs'!B18)),1),"")) -> 1 | L7: ='Pricing comparison'!E7-'Monthly operating case'!B12 -> 0.66164

Sheet Email uncertainty and cost boun
A1: Email uncertainty and cost bounds
A2: ReachPilot unit economics · Main Scenario
A4: Variable / dimension | B4: Value
A5: Email lower bound monthly | B5: =10 -> 10
A6: Email upper bound monthly | B6: =30 -> 30
A7: Minimum cost floor per lead | B7: ='Measured run and cost inputs'!B14+('Measured run and cost inputs'!B16+'Email uncertainty and cost boun'!B5)/'Monthly operating case'!B8 -> 0.2728
A8: Maximum cost floor per lead | B8: ='Measured run and cost inputs'!B15+('Measured run and cost inputs'!B16+'Email uncertainty and cost boun'!B6)/'Monthly operating case'!B8 -> 0.33086

Sheet Campaign LLM measurement
A1: Campaign LLM measurement
A2: ReachPilot unit economics · Main Scenario
A4: Variable / dimension | B4: Value
A5: Campaign LLM spend | B5: =0.102092 -> 0.102092
A6: Strict parent trace spend | B6: =0.035692 -> 0.035692
A7: Campaign input tokens | B7: =48455 -> 48455
A8: Campaign output tokens | B8: =8332 -> 8332
A9: Campaign total tokens | B9: ='Campaign LLM measurement'!B7+'Campaign LLM measurement'!B8 -> 56787
A10: Campaign traces | B10: =46 -> 46
A11: Campaign LLM calls | B11: =55 -> 55
A12: LLM tokens per qualified lead | B12: ='Campaign LLM measurement'!B9/'Measured run and cost inputs'!B6 -> 5678.7
A13: LLM spend omitted by parent match | B13: ='Campaign LLM measurement'!B5-'Campaign LLM measurement'!B6 -> 0.0664
A14: Parent match cost understatement | B14: ='Campaign LLM measurement'!B13/'Campaign LLM measurement'!B5 -> 0.65039376

Sheet Completed blended cost summary
A1: Completed blended cost summary
A2: ReachPilot unit economics · Main Scenario
A4: Variable / dimension | B4: Value
A5: Direct cost per lead low | B5: ='Measured run and cost inputs'!B14+'Measured run and cost inputs'!B18 -> 0.2755092
A6: Direct cost per lead high | B6: ='Measured run and cost inputs'!B15+'Measured run and cost inputs'!B18 -> 0.3285692
A7: Blended cost lower bound | B7: ='Email uncertainty and cost boun'!B7+'Measured run and cost inputs'!B18 -> 0.2830092
A8: Blended cost upper bound | B8: ='Email uncertainty and cost boun'!B8+'Measured run and cost inputs'!B18 -> 0.3410692
A9: Projected Bedrock tokens monthly | B9: ='Campaign LLM measurement'!B12*'Monthly operating case'!B8 -> 22714800
A10: Monthly service cost low | B10: ='Monthly operating case'!B8*'Completed blended cost summary'!B5+'Measured run and cost inputs'!B19 -> 1142.0368
A11: Monthly service cost high | B11: ='Monthly operating case'!B8*'Completed blended cost summary'!B6+'Measured run and cost inputs'!B19 -> 1354.2768

Sheet Completed pricing profitability
A1: Completed pricing profitability
A2: ReachPilot unit economics · Main Scenario
A4: Variable / dimension | B4: Revenue per customer | C4: Monthly plan revenue | D4: Monthly service surplus low | E4: Monthly service surplus high | F4: Service margin low quote | G4: Service margin high quote | H4: Service break-even low quote | I4: Full break-even customers high | J4: Break-even upper overhead high quote
A5: $0.80 per lead | B5: ='Pricing comparison'!B5+'Pricing comparison'!C5*'Monthly operating case'!B6 -> 80 | C5: ='Completed pricing profitability'!B5*'Monthly operating case'!B5 -> 3200 | D5: ='Completed pricing profitability'!C5-'Completed blended cost summary'!B10 -> 2057.9632 | E5: ='Completed pricing profitability'!C5-'Completed blended cost summary'!B11 -> 1845.7232 | F5: =IFERROR('Completed pricing profitability'!D5/'Completed pricing profitability'!C5,"") -> 0.6431135 | G5: =IFERROR('Completed pricing profitability'!E5/'Completed pricing profitability'!C5,"") -> 0.5767885 | H5: =IF(IF(IF(ISERROR('Completed pricing profitability'!B5>'Monthly operating case'!B6*'Completed blended cost summary'!B5),'Completed pricing profitability'!B5>'Monthly operating case'!B6*'Completed blended cost summary'!B5,IF('Completed pricing profitability'!B5="","",'Completed pricing profitability'!B5>'Monthly operating case'!B6*'Completed blended cost summary'!B5))="",FALSE,IF(ISERROR('Completed pricing profitability'!B5>'Monthly operating case'!B6*'Completed blended cost summary'!B5),'Completed pricing profitability'!B5>'Monthly operating case'!B6*'Completed blended cost summary'!B5,IF('Completed pricing profitability'!B5="","",'Completed pricing profitability'!B5>'Monthly operating case'!B6*'Completed blended cost summary'!B5))),CEILING('Measured run and cost inputs'!B19/('Completed pricing profitability'!B5-'Monthly operating case'!B6*'Completed blended cost summary'!B5),1),"") -> 1 | I5: =IF('Measured run and cost inputs'!B18="","",IF(IF(IF(ISERROR('Completed pricing profitability'!B5>'Monthly operating case'!B6*('Measured run and cost inputs'!B15+'Measured run and cost inputs'!B18)),'Completed pricing profitability'!B5>'Monthly operating case'!B6*('Measured run and cost inputs'!B15+'Measured run and cost inputs'!B18),IF('Completed pricing profitability'!B5="","",'Completed pricing profitability'!B5>'Monthly operating case'!B6*('Measured run and cost inputs'!B15+'Measured run and cost inputs'!B18)))="",FALSE,IF(ISERROR('Completed pricing profitability'!B5>'Monthly operating case'!B6*('Measured run and cost inputs'!B15+'Measured run and cost inputs'!B18)),'Completed pricing profitability'!B5>'Monthly operating case'!B6*('Measured run and cost inputs'!B15+'Measured run and cost inputs'!B18),IF('Completed pricing profitability'!B5="","",'Completed pricing profitability'!B5>'Monthly operating case'!B6*('Measured run and cost inputs'!B15+'Measured run and cost inputs'!B18)))),CEILING('Measured run and cost inputs'!B19/('Completed pricing profitability'!B5-'Monthly operating case'!B6*('Measured run and cost inputs'!B15+'Measured run and cost inputs'!B18)),1),"")) -> 1 | J5: =IF(IF(IF(ISERROR('Completed pricing profitability'!B5>'Monthly operating case'!B6*'Completed blended cost summary'!B6),'Completed pricing profitability'!B5>'Monthly operating case'!B6*'Completed blended cost summary'!B6,IF('Completed pricing profitability'!B5="","",'Completed pricing profitability'!B5>'Monthly operating case'!B6*'Completed blended cost summary'!B6))="",FALSE,IF(ISERROR('Completed pricing profitability'!B5>'Monthly operating case'!B6*'Completed blended cost summary'!B6),'Completed pricing profitability'!B5>'Monthly operating case'!B6*'Completed blended cost summary'!B6,IF('Completed pricing profitability'!B5="","",'Completed pricing profitability'!B5>'Monthly operating case'!B6*'Completed blended cost summary'!B6))),CEILING(('Measured run and cost inputs'!B16+'Email uncertainty and cost boun'!B6)/('Completed pricing profitability'!B5-'Monthly operating case'!B6*'Completed blended cost summary'!B6),1),"") -> 2
A6: $49 subscription | B6: ='Pricing comparison'!B6+'Pricing comparison'!C6*'Monthly operating case'!B6 -> 49 | C6: ='Completed pricing profitability'!B6*'Monthly operating case'!B5 -> 1960 | D6: ='Completed pricing profitability'!C6-'Completed blended cost summary'!B10 -> 817.9632 | E6: ='Completed pricing profitability'!C6-'Completed blended cost summary'!B11 -> 605.7232 | F6: =IFERROR('Completed pricing profitability'!D6/'Completed pricing profitability'!C6,"") -> 0.41732816 | G6: =IFERROR('Completed pricing profitability'!E6/'Completed pricing profitability'!C6,"") -> 0.30904245 | H6: =IF(IF(IF(ISERROR('Completed pricing profitability'!B6>'Monthly operating case'!B6*'Completed blended cost summary'!B5),'Completed pricing profitability'!B6>'Monthly operating case'!B6*'Completed blended cost summary'!B5,IF('Completed pricing profitability'!B6="","",'Completed pricing profitability'!B6>'Monthly operating case'!B6*'Completed blended cost summary'!B5))="",FALSE,IF(ISERROR('Completed pricing profitability'!B6>'Monthly operating case'!B6*'Completed blended cost summary'!B5),'Completed pricing profitability'!B6>'Monthly operating case'!B6*'Completed blended cost summary'!B5,IF('Completed pricing profitability'!B6="","",'Completed pricing profitability'!B6>'Monthly operating case'!B6*'Completed blended cost summary'!B5))),CEILING('Measured run and cost inputs'!B19/('Completed pricing profitability'!B6-'Monthly operating case'!B6*'Completed blended cost summary'!B5),1),"") -> 2 | I6: =IF('Measured run and cost inputs'!B18="","",IF(IF(IF(ISERROR('Completed pricing profitability'!B6>'Monthly operating case'!B6*('Measured run and cost inputs'!B15+'Measured run and cost inputs'!B18)),'Completed pricing profitability'!B6>'Monthly operating case'!B6*('Measured run and cost inputs'!B15+'Measured run and cost inputs'!B18),IF('Completed pricing profitability'!B6="","",'Completed pricing profitability'!B6>'Monthly operating case'!B6*('Measured run and cost inputs'!B15+'Measured run and cost inputs'!B18)))="",FALSE,IF(ISERROR('Completed pricing profitability'!B6>'Monthly operating case'!B6*('Measured run and cost inputs'!B15+'Measured run and cost inputs'!B18)),'Completed pricing profitability'!B6>'Monthly operating case'!B6*('Measured run and cost inputs'!B15+'Measured run and cost inputs'!B18),IF('Completed pricing profitability'!B6="","",'Completed pricing profitability'!B6>'Monthly operating case'!B6*('Measured run and cost inputs'!B15+'Measured run and cost inputs'!B18)))),CEILING('Measured run and cost inputs'!B19/('Completed pricing profitability'!B6-'Monthly operating case'!B6*('Measured run and cost inputs'!B15+'Measured run and cost inputs'!B18)),1),"")) -> 3 | J6: =IF(IF(IF(ISERROR('Completed pricing profitability'!B6>'Monthly operating case'!B6*'Completed blended cost summary'!B6),'Completed pricing profitability'!B6>'Monthly operating case'!B6*'Completed blended cost summary'!B6,IF('Completed pricing profitability'!B6="","",'Completed pricing profitability'!B6>'Monthly operating case'!B6*'Completed blended cost summary'!B6))="",FALSE,IF(ISERROR('Completed pricing profitability'!B6>'Monthly operating case'!B6*'Completed blended cost summary'!B6),'Completed pricing profitability'!B6>'Monthly operating case'!B6*'Completed blended cost summary'!B6,IF('Completed pricing profitability'!B6="","",'Completed pricing profitability'!B6>'Monthly operating case'!B6*'Completed blended cost summary'!B6))),CEILING(('Measured run and cost inputs'!B16+'Email uncertainty and cost boun'!B6)/('Completed pricing profitability'!B6-'Monthly operating case'!B6*'Completed blended cost summary'!B6),1),"") -> 4
A7: $99 subscription | B7: ='Pricing comparison'!B7+'Pricing comparison'!C7*'Monthly operating case'!B6 -> 99 | C7: ='Completed pricing profitability'!B7*'Monthly operating case'!B5 -> 3960 | D7: ='Completed pricing profitability'!C7-'Completed blended cost summary'!B10 -> 2817.9632 | E7: ='Completed pricing profitability'!C7-'Completed blended cost summary'!B11 -> 2605.7232 | F7: =IFERROR('Completed pricing profitability'!D7/'Completed pricing profitability'!C7,"") -> 0.71160687 | G7: =IFERROR('Completed pricing profitability'!E7/'Completed pricing profitability'!C7,"") -> 0.65801091 | H7: =IF(IF(IF(ISERROR('Completed pricing profitability'!B7>'Monthly operating case'!B6*'Completed blended cost summary'!B5),'Completed pricing profitability'!B7>'Monthly operating case'!B6*'Completed blended cost summary'!B5,IF('Completed pricing profitability'!B7="","",'Completed pricing profitability'!B7>'Monthly operating case'!B6*'Completed blended cost summary'!B5))="",FALSE,IF(ISERROR('Completed pricing profitability'!B7>'Monthly operating case'!B6*'Completed blended cost summary'!B5),'Completed pricing profitability'!B7>'Monthly operating case'!B6*'Completed blended cost summary'!B5,IF('Completed pricing profitability'!B7="","",'Completed pricing profitability'!B7>'Monthly operating case'!B6*'Completed blended cost summary'!B5))),CEILING('Measured run and cost inputs'!B19/('Completed pricing profitability'!B7-'Monthly operating case'!B6*'Completed blended cost summary'!B5),1),"") -> 1 | I7: =IF('Measured run and cost inputs'!B18="","",IF(IF(IF(ISERROR('Completed pricing profitability'!B7>'Monthly operating case'!B6*('Measured run and cost inputs'!B15+'Measured run and cost inputs'!B18)),'Completed pricing profitability'!B7>'Monthly operating case'!B6*('Measured run and cost inputs'!B15+'Measured run and cost inputs'!B18),IF('Completed pricing profitability'!B7="","",'Completed pricing profitability'!B7>'Monthly operating case'!B6*('Measured run and cost inputs'!B15+'Measured run and cost inputs'!B18)))="",FALSE,IF(ISERROR('Completed pricing profitability'!B7>'Monthly operating case'!B6*('Measured run and cost inputs'!B15+'Measured run and cost inputs'!B18)),'Completed pricing profitability'!B7>'Monthly operating case'!B6*('Measured run and cost inputs'!B15+'Measured run and cost inputs'!B18),IF('Completed pricing profitability'!B7="","",'Completed pricing profitability'!B7>'Monthly operating case'!B6*('Measured run and cost inputs'!B15+'Measured run and cost inputs'!B18)))),CEILING('Measured run and cost inputs'!B19/('Completed pricing profitability'!B7-'Monthly operating case'!B6*('Measured run and cost inputs'!B15+'Measured run and cost inputs'!B18)),1),"")) -> 1 | J7: =IF(IF(IF(ISERROR('Completed pricing profitability'!B7>'Monthly operating case'!B6*'Completed blended cost summary'!B6),'Completed pricing profitability'!B7>'Monthly operating case'!B6*'Completed blended cost summary'!B6,IF('Completed pricing profitability'!B7="","",'Completed pricing profitability'!B7>'Monthly operating case'!B6*'Completed blended cost summary'!B6))="",FALSE,IF(ISERROR('Completed pricing profitability'!B7>'Monthly operating case'!B6*'Completed blended cost summary'!B6),'Completed pricing profitability'!B7>'Monthly operating case'!B6*'Completed blended cost summary'!B6,IF('Completed pricing profitability'!B7="","",'Completed pricing profitability'!B7>'Monthly operating case'!B6*'Completed blended cost summary'!B6))),CEILING(('Measured run and cost inputs'!B16+'Email uncertainty and cost boun'!B6)/('Completed pricing profitability'!B7-'Monthly operating case'!B6*'Completed blended cost summary'!B6),1),"") -> 1
